LICENSE
MANIFEST.in
README
requirements.txt
setup.py
django_edumetadata.egg-info/PKG-INFO
django_edumetadata.egg-info/SOURCES.txt
django_edumetadata.egg-info/dependency_links.txt
django_edumetadata.egg-info/requires.txt
django_edumetadata.egg-info/top_level.txt
doc_src/.DS_Store
doc_src/Makefile
doc_src/conf.py
doc_src/getting_started.rst
doc_src/grades.rst
doc_src/index.rst
doc_src/installation.rst
doc_src/make.bat
doc_src/registering_models.rst
doc_src/subjectsanddisciplines.rst
doc_src/timeperiods.rst
doc_src/_build/doctrees/environment.pickle
doc_src/_build/doctrees/getting_started.doctree
doc_src/_build/doctrees/grades.doctree
doc_src/_build/doctrees/index.doctree
doc_src/_build/doctrees/installation.doctree
doc_src/_build/doctrees/registering_models.doctree
doc_src/_build/doctrees/subjectsanddisciplines.doctree
doc_src/_build/doctrees/timeperiods.doctree
doc_src/_build/doctrees/reference/index.doctree
doc_src/_build/doctrees/reference/settings.doctree
doc_src/_static/breadcrumb_background.png
doc_src/_static/default.css
doc_src/_static/documentation.png
doc_src/_static/header_sm_mid.png
doc_src/_static/scrn1.png
doc_src/_static/scrn2.png
doc_src/_static/searchfield_leftcap.png
doc_src/_static/searchfield_repeat.png
doc_src/_static/searchfield_rightcap.png
doc_src/_static/title_background.png
doc_src/_static/toc.js
doc_src/_static/triangle_closed.png
doc_src/_static/triangle_left.png
doc_src/_static/triangle_open.png
doc_src/_templates/layout.html
doc_src/code_examples/register1.py
doc_src/code_examples/register_example.py
doc_src/reference/index.rst
doc_src/reference/settings.rst
docs/.buildinfo
docs/genindex.html
docs/getting_started.html
docs/grades.html
docs/index.html
docs/installation.html
docs/objects.inv
docs/registering_models.html
docs/search.html
docs/searchindex.js
docs/subjectsanddisciplines.html
docs/timeperiods.html
docs/_sources/getting_started.txt
docs/_sources/grades.txt
docs/_sources/index.txt
docs/_sources/installation.txt
docs/_sources/registering_models.txt
docs/_sources/subjectsanddisciplines.txt
docs/_sources/timeperiods.txt
docs/_sources/reference/index.txt
docs/_sources/reference/settings.txt
docs/_static/basic.css
