Metadata-Version: 1.0
Name: django-edumetadata
Version: 0.7
Summary: django-edumetadata
Home-page: https://github.com/organizations/Natgeoed/django-edumetadata
Author: coordt
Author-email: coordt@ngs.org
License: UNKNOWN
Platform: UNKNOWN
Classifier: License :: OSI Approved :: Apache Software License
Classifier: Framework :: Django
